{"cameraMode":{"drawMode":0,"name":"Shaded","section":"Shading Mode"},"sceneLighting":true,"audioPlay":false,"sceneViewState":{"m_AlwaysRefresh":false,"showFog":true,"showSkybox":true,"showFlares":true,"showImageEffects":true,"showParticleSystems":true,"showVisualEffectGraphs":true,"m_FxEnabled":true},"in2DMode":false,"pivot":{"x":756.0527954101563,"y":538.8838500976563,"z":92.15118408203125},"rotation":{"x":0.1377386450767517,"y":0.043066076934337619,"z":-0.005994534585624933,"w":0.9895145893096924},"size":457.87298583984377,"orthographic":false}